twelve_tone/__init__.py
twelve_tone/__main__.py
twelve_tone/cli.py
twelve_tone/composer.py
twelve_tone/midi.py
twelve_tone-0.4.2.dist-info/AUTHORS.rst
twelve_tone-0.4.2.dist-info/LICENSE
twelve_tone-0.4.2.dist-info/METADATA
twelve_tone-0.4.2.dist-info/WHEEL
twelve_tone-0.4.2.dist-info/entry_points.txt
twelve_tone-0.4.2.dist-info/top_level.txt
twelve_tone-0.4.2.dist-info/RECORD
