Metadata-Version: 2.1
Name: twelve-tone
Version: 0.4.2
Summary: Twelve-tone matrix to generate dodecaphonic melodies
Home-page: https://github.com/accraze/python-twelve-tone
Author: Andy Craze
Author-email: accraze@gmail.com
License: BSD
Keywords: music,composition,matrix,atonal,midi
Platform: UNKNOWN
Classifier: Development Status :: 5 - Production/Stable
Classifier: Intended Audience :: Developers
Classifier: License :: OSI Approved :: BSD License
Classifier: Operating System :: Unix
Classifier: Operating System :: POSIX
Classifier: Operating System :: Microsoft :: Windows
Classifier: Programming Language :: Python
Classifier: Programming Language :: Python :: 2.7
Classifier: Programming Language :: Python :: 3
Classifier: Programming Language :: Python :: 3.3
Classifier: Programming Language :: Python :: 3.4
Classifier: Programming Language :: Python :: 3.5
Classifier: Topic :: Utilities
Requires-Dist: click
Requires-Dist: numpy
Requires-Dist: miditime
